Workbook
Name aporte: APP!$G$18
Name Despesas: APP!$G$12
Name patrimonio: APP!$G$21
Name perfil: APP!$C$33
Name qtd_anos: APP!$G$19
Name rendimento_carteira: APP!$G$13
Name salario: APP!$G$11
Name sugestao_investimento: APP!$G$14
Name taxa_mensal: APP!$G$20

Sheet APP
D2: SIMULADOR DE INVESTIMENTOS EM FIIs
D4: Aportes mensais, patrimônio projetado e renda de dividendos
D6: Cenário didático com FIIs reais • referência dos rendimentos: set/out 2026
B10: CONFIGURAÇÕES
B11: Salário de exemplo | G11: 3100
B12: Despesas (mês) | G12: =salario*0.5 -> 1550
B13: Rendimento da carteira (DY mensal ref.) | G13: =SUMPRODUCT($D$37:$D$42,$F$37:$F$42) -> 0.0093154
B14: Sugestão de investimento (30%) | G14: =(salario-Despesas)*0.3 -> 465
B15: Perfil selecionado | G15: =perfil -> Moderado
B17: INVESTIMENTO MENSAL
B18: Quanto investir por mês? | G18: 775
B19: Por quantos anos? | G19: 10
B20: Taxa de rendimento mensal? | G20: =rendimento_carteira -> 0.0093154
B21: Patrimônio acumulado? | G21: =FV(taxa_mensal,qtd_anos*12,aporte*-1) -> 169925.42
B22: Dividendos mensais estimados? | G22: =patrimonio*rendimento_carteira -> 1582.9233
B24: PROJEÇÃO DE CENÁRIOS
B25: Prazo (anos) | C25: Descrição | D25: Patrimônio | F25: Dividendos/mês | G25: Aportes totais
B26: 2 | C26: ="Em "&B26&" anos" -> Em 2 anos | D26: =FV(taxa_mensal,$B26*12,aporte*-1) -> 20735.594 | F26: =D26*rendimento_carteira -> 193.16036 | G26: =aporte*$B26*12 -> 18600
B27: 5 | C27: ="Em "&B27&" anos" -> Em 5 anos | D27: =FV(taxa_mensal,$B27*12,aporte*-1) -> 61920.057 | F27: =D27*rendimento_carteira -> 576.81009 | G27: =aporte*$B27*12 -> 46500
B28: 10 | C28: ="Em "&B28&" anos" -> Em 10 anos | D28: =FV(taxa_mensal,$B28*12,aporte*-1) -> 169925.42 | F28: =D28*rendimento_carteira -> 1582.9233 | G28: =aporte*$B28*12 -> 93000
B29: 20 | C29: ="Em "&B29&" anos" -> Em 20 anos | D29: =FV(taxa_mensal,$B29*12,aporte*-1) -> 686920.39 | F29: =D29*rendimento_carteira -> 6398.9382 | G29: =aporte*$B29*12 -> 186000
B30: 30 | C30: ="Em "&B30&" anos" -> Em 30 anos | D30: =FV(taxa_mensal,$B30*12,aporte*-1) -> 2259868.1 | F30: =D30*rendimento_carteira -> 21051.575 | G30: =aporte*$B30*12 -> 279000
B32: DISTRIBUIÇÃO DO APORTE POR PERFIL
B33: PERFIL | C33: Moderado
B34: VALOR A SER INVESTIDO POR MÊS | C34: =aporte -> 775
B36: TIPO DE FII | C36: FII REAL DE REFERÊNCIA | D36: PERCENTUAL SUGERIDO | E36: VALOR DO APORTE | F36: DY MENSAL REF. | G36: RENDA/MÊS DO NOVO APORTE
B37: PAPEL | C37: =VLOOKUP($C$33&"-"&$B37,Planilha2!$A$4:$J$21,5,FALSE) -> KNCR11 | D37: =VLOOKUP($C$33&"-"&$B37,Planilha2!$A$4:$J$21,4,FALSE) -> 0.3 | E37: =D37*$C$34 -> 232.5 | F37: =VLOOKUP($C$33&"-"&$B37,Planilha2!$A$4:$J$21,6,FALSE) -> 0.01062 | G37: =E37*F37 -> 2.46915
B38: TIJOLO | C38: =VLOOKUP($C$33&"-"&$B38,Planilha2!$A$4:$J$21,5,FALSE) -> HGLG11 | D38: =VLOOKUP($C$33&"-"&$B38,Planilha2!$A$4:$J$21,4,FALSE) -> 0.3 | E38: =D38*$C$34 -> 232.5 | F38: =VLOOKUP($C$33&"-"&$B38,Planilha2!$A$4:$J$21,6,FALSE) -> 0.007908 | G38: =E38*F38 -> 1.83861
B39: HÍBRIDOS | C39: =VLOOKUP($C$33&"-"&$B39,Planilha2!$A$4:$J$21,5,FALSE) -> KNRI11 | D39: =VLOOKUP($C$33&"-"&$B39,Planilha2!$A$4:$J$21,4,FALSE) -> 0.15 | E39: =D39*$C$34 -> 116.25 | F39: =VLOOKUP($C$33&"-"&$B39,Planilha2!$A$4:$J$21,6,FALSE) -> 0.007006 | G39: =E39*F39 -> 0.8144475
B40: FOFs | C40: =VLOOKUP($C$33&"-"&$B40,Planilha2!$A$4:$J$21,5,FALSE) -> KFOF11 | D40: =VLOOKUP($C$33&"-"&$B40,Planilha2!$A$4:$J$21,4,FALSE) -> 0.1 | E40: =D40*$C$34 -> 77.5 | F40: =VLOOKUP($C$33&"-"&$B40,Planilha2!$A$4:$J$21,6,FALSE) -> 0.01026 | G40: =E40*F40 -> 0.79515
B41: DESENVOLVIMENTO | C41: =VLOOKUP($C$33&"-"&$B41,Planilha2!$A$4:$J$21,5,FALSE) -> TGAR11 | D41: =VLOOKUP($C$33&"-"&$B41,Planilha2!$A$4:$J$21,4,FALSE) -> 0.05 | E41: =D41*$C$34 -> 38.75 | F41: =VLOOKUP($C$33&"-"&$B41,Planilha2!$A$4:$J$21,6,FALSE) -> 0.016018 | G41: =E41*F41 -> 0.6206975
B42: HOTELARIAS | C42: =VLOOKUP($C$33&"-"&$B42,Planilha2!$A$4:$J$21,5,FALSE) -> HTMX11 | D42: =VLOOKUP($C$33&"-"&$B42,Planilha2!$A$4:$J$21,4,FALSE) -> 0.1 | E42: =D42*$C$34 -> 77.5 | F42: =VLOOKUP($C$33&"-"&$B42,Planilha2!$A$4:$J$21,6,FALSE) -> 0.008792 | G42: =E42*F42 -> 0.68138
B43: TOTAL / CARTEIRA | D43: =SUM(D37:D42) -> 1 | E43: =SUM(E37:E42) -> 775 | F43: =SUMPRODUCT(D37:D42,F37:F42) -> 0.0093154 | G43: =SUM(G37:G42) -> 7.219435
B45: Importante: os FIIs e rendimentos são referências reais de mercado consultadas em 15/10/2026. Rendimentos passados não garantem resultados futuros. Os percentuais por perfil são exemplos didáticos, não recomendação de investimento.

Sheet Planilha2
A1: PLANILHA DE APOIO — PERFIS, CHAVES COMPOSTAS E FIIs REAIS
A2: A coluna CHAVE combina Perfil + Tipo de FII e permite que o PROCV encontre a alocação, o ticker e o DY correspondente.
A3: CHAVE | B3: PERFIL | C3: TIPO DE FII | D3: % | E3: FII REF. | F3: DY MENSAL REF. | G3: ÚLTIMO REND./COTA | H3: COTAÇÃO BASE | I3: DATA-BASE | J3: FONTE | L3: PERFIL | M3: SOMA %
A4: Conservador-PAPEL | B4: Conservador | C4: PAPEL | D4: 0.4 | E4: KNCR11 | F4: 0.01062 | G4: 1.13 | H4: 106.4 | I4: 30/09/2026 | J4: https://statusinvest.com.br/fundos-imobiliarios/kncr11 | L4: Conservador | M4: =SUMIF($B$4:$B$21,L4,$D$4:$D$21) -> 1
A5: Conservador-TIJOLO | B5: Conservador | C5: TIJOLO | D5: 0.3 | E5: HGLG11 | F5: 0.007908 | G5: 1.17 | H5: 147.95 | I5: 30/09/2026 | J5: https://statusinvest.com.br/fundos-imobiliarios/hglg11 | L5: Moderado | M5: =SUMIF($B$4:$B$21,L5,$D$4:$D$21) -> 1
A6: Conservador-HÍBRIDOS | B6: Conservador | C6: HÍBRIDOS | D6: 0.15 | E6: KNRI11 | F6: 0.007006 | G6: 1.1 | H6: 157.01 | I6: 30/09/2026 | J6: https://statusinvest.com.br/fundos-imobiliarios/knri11 | L6: Agressivo | M6: =SUMIF($B$4:$B$21,L6,$D$4:$D$21) -> 1
A7: Conservador-FOFs | B7: Conservador | C7: FOFs | D7: 0.1 | E7: KFOF11 | F7: 0.01026 | G7: 0.8 | H7: 77.97 | I7: 30/09/2026 | J7: https://statusinvest.com.br/fundos-imobiliarios/kfof11
A8: Conservador-DESENVOLVIMENTO | B8: Conservador | C8: DESENVOLVIMENTO | D8: 0 | E8: TGAR11 | F8: 0.016018 | G8: 0.7 | H8: 43.7 | I8: 30/09/2026 | J8: https://statusinvest.com.br/fundos-imobiliarios/tgar11 | L8: PERFIL | M8: DY PONDERADO
A9: Conservador-HOTELARIAS | B9: Conservador | C9: HOTELARIAS | D9: 0.05 | E9: HTMX11 | F9: 0.008792 | G9: 1.2 | H9: 136.48 | I9: 30/09/2026 | J9: https://statusinvest.com.br/fundos-imobiliarios/htmx11 | L9: Conservador | M9: =SUMPRODUCT(($B$4:$B$21=L9)*$D$4:$D$21*$F$4:$F$21) -> 0.0091369
A10: Moderado-PAPEL | B10: Moderado | C10: PAPEL | D10: 0.3 | E10: KNCR11 | F10: 0.01062 | G10: 1.13 | H10: 106.4 | I10: 30/09/2026 | J10: https://statusinvest.com.br/fundos-imobiliarios/kncr11 | L10: Moderado | M10: =SUMPRODUCT(($B$4:$B$21=L10)*$D$4:$D$21*$F$4:$F$21) -> 0.0093154
A11: Moderado-TIJOLO | B11: Moderado | C11: TIJOLO | D11: 0.3 | E11: HGLG11 | F11: 0.007908 | G11: 1.17 | H11: 147.95 | I11: 30/09/2026 | J11: https://statusinvest.com.br/fundos-imobiliarios/hglg11 | L11: Agressivo | M11: =SUMPRODUCT(($B$4:$B$21=L11)*$D$4:$D$21*$F$4:$F$21) -> 0.0103049
A12: Moderado-HÍBRIDOS | B12: Moderado | C12: HÍBRIDOS | D12: 0.15 | E12: KNRI11 | F12: 0.007006 | G12: 1.1 | H12: 157.01 | I12: 30/09/2026 | J12: https://statusinvest.com.br/fundos-imobiliarios/knri11
A13: Moderado-FOFs | B13: Moderado | C13: FOFs | D13: 0.1 | E13: KFOF11 | F13: 0.01026 | G13: 0.8 | H13: 77.97 | I13: 30/09/2026 | J13: https://statusinvest.com.br/fundos-imobiliarios/kfof11
A14: Moderado-DESENVOLVIMENTO | B14: Moderado | C14: DESENVOLVIMENTO | D14: 0.05 | E14: TGAR11 | F14: 0.016018 | G14: 0.7 | H14: 43.7 | I14: 30/09/2026 | J14: https://statusinvest.com.br/fundos-imobiliarios/tgar11
A15: Moderado-HOTELARIAS | B15: Moderado | C15: HOTELARIAS | D15: 0.1 | E15: HTMX11 | F15: 0.008792 | G15: 1.2 | H15: 136.48 | I15: 30/09/2026 | J15: https://statusinvest.com.br/fundos-imobiliarios/htmx11
A16: Agressivo-PAPEL | B16: Agressivo | C16: PAPEL | D16: 0.2 | E16: KNCR11 | F16: 0.01062 | G16: 1.13 | H16: 106.4 | I16: 30/09/2026 | J16: https://statusinvest.com.br/fundos-imobiliarios/kncr11
A17: Agressivo-TIJOLO | B17: Agressivo | C17: TIJOLO | D17: 0.2 | E17: HGLG11 | F17: 0.007908 | G17: 1.17 | H17: 147.95 | I17: 30/09/2026 | J17: https://statusinvest.com.br/fundos-imobiliarios/hglg11
A18: Agressivo-HÍBRIDOS | B18: Agressivo | C18: HÍBRIDOS | D18: 0.15 | E18: KNRI11 | F18: 0.007006 | G18: 1.1 | H18: 157.01 | I18: 30/09/2026 | J18: https://statusinvest.com.br/fundos-imobiliarios/knri11
A19: Agressivo-FOFs | B19: Agressivo | C19: FOFs | D19: 0.1 | E19: KFOF11 | F19: 0.01026 | G19: 0.8 | H19: 77.97 | I19: 30/09/2026 | J19: https://statusinvest.com.br/fundos-imobiliarios/kfof11
A20: Agressivo-DESENVOLVIMENTO | B20: Agressivo | C20: DESENVOLVIMENTO | D20: 0.2 | E20: TGAR11 | F20: 0.016018 | G20: 0.7 | H20: 43.7 | I20: 30/09/2026 | J20: https://statusinvest.com.br/fundos-imobiliarios/tgar11
A21: Agressivo-HOTELARIAS | B21: Agressivo | C21: HOTELARIAS | D21: 0.15 | E21: HTMX11 | F21: 0.008792 | G21: 1.2 | H21: 136.48 | I21: 30/09/2026 | J21: https://statusinvest.com.br/fundos-imobiliarios/htmx11
A23: Nota metodológica: os percentuais dos perfis foram definidos apenas para fins didáticos neste projeto e somam 100% em cada perfil. O DY mensal de referência usa o último rendimento e a cotação-base apresentados nas páginas consultadas. Esses dados mudam ao longo do tempo e não constituem recomendação de compra, venda ou manutenção.
